track2p/__init__.py
track2p/__main__.py
track2p/t2p.py
track2p/gui/__init__.py
track2p/gui/cell_plot.py
track2p/gui/central_widget.py
track2p/gui/custom_wd.py
track2p/gui/data_management.py
track2p/gui/fluo_plot.py
track2p/gui/import_wd.py
track2p/gui/main_wd.py
track2p/gui/raster_wd.py
track2p/gui/roi_plot.py
track2p/gui/statusbar.py
track2p/gui/t2p_wd.py
track2p/gui/toolbar.py
track2p/gui/window_manager.py
track2p/io/__init__.py
track2p/io/loaders.py
track2p/io/s2p_loaders.py
track2p/io/savers.py
track2p/io/utils.py
track2p/match/__init__.py
track2p/match/loop.py
track2p/match/utils.py
track2p/ops/__init__.py
track2p/ops/default.py
track2p/plot/__init__.py
track2p/plot/output.py
track2p/plot/progress.py
track2p/plot/utils.py
track2p/register/__init__.py
track2p/register/elastix.py
track2p/register/loop.py
track2p/register/utils.py
track2p/resources/logo.png
track2p-0.6.2.dist-info/LICENSE
track2p-0.6.2.dist-info/METADATA
track2p-0.6.2.dist-info/WHEEL
track2p-0.6.2.dist-info/top_level.txt
track2p-0.6.2.dist-info/RECORD
