Metadata-Version: 2.1
Name: track2p
Version: 0.6.2
License-File: LICENSE
Requires-Dist: numpy ==2.0.2
Requires-Dist: matplotlib ==3.9.4
Requires-Dist: scikit-image ==0.24.0
Requires-Dist: itk ==5.4.3
Requires-Dist: PyQt5 ==5.15.11
Requires-Dist: qtpy ==2.4.3
Requires-Dist: tqdm ==4.67.1
Requires-Dist: scikit-learn ==1.6.1
Requires-Dist: openTSNE ==1.0.2
Requires-Dist: pandas ==2.2.3
Requires-Dist: itk-elastix ==0.23.0
